oxpower/__init__.py
oxpower-6.6.7.dist-info/LICENSE
oxpower-6.6.7.dist-info/METADATA
oxpower-6.6.7.dist-info/WHEEL
oxpower-6.6.7.dist-info/top_level.txt
oxpower-6.6.7.dist-info/RECORD
