Metadata-Version: 2.1
Name: oxpower
Version: 6.6.7
Summary: A Python Package
Home-page: https://t.me/DKBOTZ
Author: Don
Author-email: dkbotzhelp@gmail.com
License: MIT
Keywords: python
Classifier: Development Status :: 1 - Planning
Classifier: Intended Audience :: Developers
Classifier: Programming Language :: Python :: 3
Classifier: Operating System :: Unix
Classifier: Operating System :: MacOS :: MacOS X
Classifier: Operating System :: Microsoft :: Windows
License-File: LICENSE
Requires-Dist: oxpower
Requires-Dist: youtube-search
Requires-Dist: yt-dlp
Requires-Dist: spotdl
Requires-Dist: yt-dl
